{
 "b1b_void": {
  "modulus": 0.19421162791639254,
  "peak_stress": 0.014882227390388764,
  "peak_strain": 0.1050330101290684,
  "toughness": 0.0009777673391711892,
  "events": [],
  "initial_cores": 0,
  "final_cores": 0
 },
 "b2_dipole": {
  "modulus": 0.20280587493672947,
  "peak_stress": 0.01439615840710421,
  "peak_strain": 0.1050330101290684,
  "toughness": 0.000902321151183771,
  "events": [
   {
    "exx": 0.09678652927479403,
    "d_cores": -2,
    "cores": 0
   }
  ],
  "initial_cores": 2,
  "final_cores": 0
 },
 "b3_polycrystal": {
  "modulus": 0.08135756787246162,
  "peak_stress": 0.003872107231963817,
  "peak_strain": 0.09952849559798094,
  "toughness": 0.0002830398031573526,
  "events": [
   {
    "exx": 0.0024999999999999467,
    "d_cores": -2,
    "cores": 190
   },
   {
    "exx": 0.005006249999999879,
    "d_cores": -4,
    "cores": 186
   },
   {
    "exx": 0.007518765624999757,
    "d_cores": -1,
    "cores": 185
   },
   {
    "exx": 0.010037562539062295,
    "d_cores": -3,
    "cores": 182
   },
   {
    "exx": 0.012562656445409992,
    "d_cores": -1,
    "cores": 181
   },
   {
    "exx": 0.015094063086523501,
    "d_cores": -2,
    "cores": 179
   },
   {
    "exx": 0.01763179824423977,
    "d_cores": -7,
    "cores": 172
   },
   {
    "exx": 0.020175877739850412,
    "d_cores": -4,
    "cores": 168
   },
   {
    "exx": 0.02272631743420006,
    "d_cores": -2,
    "cores": 166
   },
   {
    "exx": 0.025283133227785415,
    "d_cores": -5,
    "cores": 161
   },
   {
    "exx": 0.03041595691350696,
    "d_cores": -10,
    "cores": 151
   },
   {
    "exx": 0.03557447679780501,
    "d_cores": -4,
    "cores": 147
   },
   {
    "exx": 0.03816341298979942,
    "d_cores": -3,
    "cores": 144
   },
   {
    "exx": 0.040758821522273836,
    "d_cores": -3,
    "cores": 141
   },
   {
    "exx": 0.04336071857607937,
    "d_cores": -1,
    "cores": 140
   },
   {
    "exx": 0.045969120372519434,
    "d_cores": 3,
    "cores": 143
   },
   {
    "exx": 0.05120550328138429,
    "d_cores": -4,
    "cores": 139
   },
   {
    "exx": 0.05383351703958761,
    "d_cores": -2,
    "cores": 137
   },
   {
    "exx": 0.05910927108426689,
    "d_cores": -5,
    "cores": 132
   },
   {
    "exx": 0.06175704426197748,
    "d_cores": -3,
    "cores": 129
   },
   {
    "exx": 0.06441143687263229,
    "d_cores": 1,
    "cores": 130
   },
   {
    "exx": 0.06974014662847572,
    "d_cores": -3,
    "cores": 127
   },
   {
    "exx": 0.07241449699504687,
    "d_cores": -6,
    "cores": 121
   },
   {
    "exx": 0.07509553323753448,
    "d_cores": -1,
    "cores": 120
   },
   {
    "exx": 0.07778327207062818,
    "d_cores": 1,
    "cores": 121
   },
   {
    "exx": 0.08317892457643161,
    "d_cores": 1,
    "cores": 122
   },
   {
    "exx": 0.08860158906759241,
    "d_cores": -2,
    "cores": 120
   },
   {
    "exx": 0.09132309304026132,
    "d_cores": -1,
    "cores": 119
   },
   {
    "exx": 0.09405140077286189,
    "d_cores": -1,
    "cores": 118
   },
   {
    "exx": 0.09678652927479403,
    "d_cores": -1,
    "cores": 117
   },
   {
    "exx": 0.09952849559798094,
    "d_cores": 2,
    "cores": 119
   },
   {
    "exx": 0.10227731683697594,
    "d_cores": 3,
    "cores": 122
   },
   {
    "exx": 0.1050330101290684,
    "d_cores": 1,
    "cores": 123
   }
  ],
  "initial_cores": 192,
  "final_cores": 123
 }
}